amrex/__init__.py
amrex/extensions/Array4.py
amrex/extensions/ArrayOfStructs.py
amrex/extensions/Iterator.py
amrex/extensions/MultiFab.py
amrex/extensions/PODVector.py
amrex/extensions/ParticleContainer.py
amrex/extensions/SmallMatrix.py
amrex/extensions/StructOfArrays.py
amrex/extensions/__init__.py
amrex/space1d/__init__.py
amrex/space1d/__init__.pyi
amrex/space1d/amrex_1d_pybind/ParallelDescriptor.pyi
amrex/space1d/amrex_1d_pybind/__init__.pyi
amrex/space2d/__init__.py
amrex/space2d/__init__.pyi
amrex/space2d/amrex_2d_pybind/ParallelDescriptor.pyi
amrex/space2d/amrex_2d_pybind/__init__.pyi
amrex/space3d/__init__.py
amrex/space3d/__init__.pyi
amrex/space3d/amrex_3d_pybind.cpython-314t-aarch64-linux-gnu.so
amrex/space3d/amrex_3d_pybind/ParallelDescriptor.pyi
amrex/space3d/amrex_3d_pybind/__init__.pyi
impactx/MADXParser.py
impactx/MADXParser.pyi
impactx/__init__.py
impactx/__init__.pyi
impactx/distribution_input_helpers.py
impactx/distribution_input_helpers.pyi
impactx/impactx_pybind.cpython-314t-aarch64-linux-gnu.so
impactx/madx_to_impactx.py
impactx/madx_to_impactx.pyi
impactx/dashboard/__init__.py
impactx/dashboard/__main__.py
impactx/dashboard/app.py
impactx/dashboard/requirements.txt
impactx/dashboard/server.py
impactx/dashboard/start.py
impactx/dashboard/Analyze/__init__.py
impactx/dashboard/Analyze/ui.py
impactx/dashboard/Analyze/over_s/__init__.py
impactx/dashboard/Analyze/over_s/plot.py
impactx/dashboard/Analyze/over_s/utils.py
impactx/dashboard/Analyze/over_s/selector/__init__.py
impactx/dashboard/Analyze/over_s/selector/components.py
impactx/dashboard/Analyze/over_s/selector/ui.py
impactx/dashboard/Input/__init__.py
impactx/dashboard/Input/defaults.py
impactx/dashboard/Input/defaults_helper.py
impactx/dashboard/Input/shared.py
impactx/dashboard/Input/style.css
impactx/dashboard/Input/utils.py
impactx/dashboard/Input/components/__init__.py
impactx/dashboard/Input/components/card.py
impactx_noacc-26.1.dist-info/METADATA
impactx_noacc-26.1.dist-info/WHEEL
impactx_noacc-26.1.dist-info/entry_points.txt
impactx_noacc-26.1.dist-info/top_level.txt
impactx_noacc-26.1.dist-info/RECORD
